drf_postman/__init__.py
drf_postman/apps.py
drf_postman/config.py
drf_postman/generator.py
drf_postman/management/__init__.py
drf_postman/management/commands/__init__.py
drf_postman/management/commands/generatepostman.py
drf_postman-0.1.0.dist-info/licenses/LICENSE.md
drf_postman-0.1.0.dist-info/METADATA
drf_postman-0.1.0.dist-info/WHEEL
drf_postman-0.1.0.dist-info/top_level.txt
drf_postman-0.1.0.dist-info/RECORD
