Metadata-Version: 2.4
Name: drf-postman
Version: 0.1.0
Summary: A Django + DRF package to generate Postman v2.1 collections with a single command
Author-email: Kevin Kimani <kimanikevin254@gmail.com>
License-Expression: MIT
Project-URL: Homepage, https://github.com/kimanikevin254/django-drf-postman
Project-URL: Repository, https://github.com/kimanikevin254/django-drf-postman
Project-URL: Issues, https://github.com/kimanikevin254/django-drf-postman/issues
Keywords: django,drf,postman,collections,api
Classifier: Development Status :: 3 - Alpha
Classifier: Intended Audience :: Developers
Classifier: Programming Language :: Python :: 3
Classifier: Programming Language :: Python :: 3.8
Classifier: Programming Language :: Python :: 3.9
Classifier: Programming Language :: Python :: 3.10
Classifier: Programming Language :: Python :: 3.11
Classifier: Programming Language :: Python :: 3.12
Classifier: Framework :: Django
Classifier: Framework :: Django :: 3.2
Classifier: Framework :: Django :: 4.0
Classifier: Framework :: Django :: 4.2
Classifier: Framework :: Django :: 5.0
Classifier: Topic :: Software Development :: Libraries :: Python Modules
Requires-Python: >=3.8
License-File: LICENSE.md
Requires-Dist: Django>=3.2
Requires-Dist: djangorestframework>=3.12
Requires-Dist: drf-spectacular>=0.26.0
Provides-Extra: dev
Requires-Dist: pytest>=7.0; extra == "dev"
Requires-Dist: pytest-cov>=4.0; extra == "dev"
Requires-Dist: pytest-django>=4.5; extra == "dev"
Dynamic: license-file
